{
  "Product": [
    {
      "id": "1",
      "ProductName": "AAA",
      "SalesVolume": 500,
      "ProductPrice": 1000,
      "isShow": true,
      "imgUrl": "https://api.fnkr.net/testimg/200x200/DDDDDD/999999/?text=img",
      "createDate": "2023-10-17T00:00:00.000+08:00"
    },
    {
      "id": "2",
      "ProductName": "BBB",
      "SalesVolume": 500,
      "ProductPrice": 1000,
      "isShow": false,
      "imgUrl": "https://api.fnkr.net/testimg/200x200/DDDDDD/999999/?text=img",
      "createDate": "2023-10-17T00:00:00.000+08:00"
    },
    {
      "id": "3",
      "ProductName": "CCC",
      "SalesVolume": 500,
      "ProductPrice": 1000,
      "isShow": true,
      "imgUrl": "https://api.fnkr.net/testimg/200x200/DDDDDD/999999/?text=img",
      "createDate": "2023-10-17T00:00:00.000+08:00"
    },
    {
      "id": "4",
      "ProductName": "DDD",
      "SalesVolume": 500,
      "ProductPrice": 1000,
      "isShow": true,
      "imgUrl": "https://api.fnkr.net/testimg/200x200/DDDDDD/999999/?text=img",
      "createDate": "2023-10-17T00:00:00.000+08:00"
    },
    {
      "id": "5",
      "ProductName": "EEE",
      "SalesVolume": 500,
      "ProductPrice": 1000,
      "isShow": true,
      "imgUrl": "https://api.fnkr.net/testimg/200x200/DDDDDD/999999/?text=img",
      "createDate": "2023-10-17T00:00:00.000+08:00"
    },
    {
      "id": "6",
      "ProductName": "FFF",
      "SalesVolume": 500,
      "ProductPrice": 1000,
      "isShow": true,
      "imgUrl": "https://api.fnkr.net/testimg/200x200/DDDDDD/999999/?text=img",
      "createDate": "2023-10-17T00:00:00.000+08:00"
    }
  ]
}
